LICENSE.txt
MANIFEST.in
README.rst
setup.py
gitifyhg/__init__.py
gitifyhg/gitexporter.py
gitifyhg/gitifyhg.py
gitifyhg/hgimporter.py
gitifyhg/util.py
gitifyhg.egg-info/PKG-INFO
gitifyhg.egg-info/SOURCES.txt
gitifyhg.egg-info/dependency_links.txt
gitifyhg.egg-info/entry_points.txt
gitifyhg.egg-info/requires.txt
gitifyhg.egg-info/top_level.txt
test/Makefile
test/aggregate-results.sh
test/sharness.sh
test/test-lib.sh
test/test_anonymous_branches.t
test/test_author.t
test/test_bookmarks.t
test/test_clone.t
test/test_clone_file_operations.t
test/test_notes.t
test/test_pull.t
test/test_push.t
test/test_push_tags.t
test/test_spaces.t
test/test_special_cases.t
test/old_tests_for_reference/test-hg-bidi.t
test/old_tests_for_reference/test-hg-hg-git.t
test/old_tests_for_reference/test-hg.t