Metadata-Version: 1.1
Name: gitifyhg
Version: 0.8.3
Summary: Use git as client for hg repos
Home-page: https://github.com/buchuki/gitifyhg
Author: Dusty Phillips
Author-email: dusty@buchuki.com
License: UNKNOWN
Platform: UNKNOWN
Classifier: Development Status :: 4 - Beta
Classifier: Intended Audience :: Developers
Classifier: Programming Language :: Python :: 2.6
Classifier: Programming Language :: Python :: 2.7
Classifier: Topic :: Software Development :: Version Control
Classifier: License :: OSI Approved :: GNU General Public License v3 or later (GPLv3+)
